mat_discover/__init__.py
mat_discover/adaptive_design.py
mat_discover/mat_discover_.py
mat_discover/meta.yaml
mat_discover/data/__init__.py
mat_discover/data/gridrdf_data/__init__.py
mat_discover/data/gridrdf_data/similarity_matrix.csv
mat_discover/tests/test_mat_discover.py
mat_discover/tests/test_suggest_next_experiment.py
mat_discover/utils/Timer.py
mat_discover/utils/__init__.py
mat_discover/utils/data.py
mat_discover/utils/extraordinary.py
mat_discover/utils/generate_elasticity_data.py
mat_discover/utils/gridrdf_helper.py
mat_discover/utils/nearest_neigh.py
mat_discover/utils/pareto.py
mat_discover/utils/plotting.py
mat_discover-2.2.9.dist-info/LICENSE
mat_discover-2.2.9.dist-info/WHEEL
mat_discover-2.2.9.dist-info/METADATA
mat_discover-2.2.9.dist-info/RECORD
