Metadata-Version: 2.1
Name: mat_discover
Version: 2.2.9
Summary: Data-driven materials discovery based on composition or structure.
Author-email: "Sterling G. Baird" <sterling.baird@utah.edu>
Classifier: License :: OSI Approved :: MIT License
Classifier: Programming Language :: Python :: 3.7
Classifier: Programming Language :: Python :: 3.8
Classifier: Programming Language :: Python :: 3.9
Classifier: Programming Language :: Python :: 3.10
Classifier: Operating System :: OS Independent
Requires-Dist: tqdm
Requires-Dist: pqdm
Requires-Dist: seaborn
Requires-Dist: scipy
Requires-Dist: hdbscan
Requires-Dist: joblib==1.1.0
Requires-Dist: cython
Requires-Dist: numba >=0.53.1
Requires-Dist: plotly >=5.6.0
Requires-Dist: kaleido
Requires-Dist: pandas
Requires-Dist: matplotlib >=3.4.3
Requires-Dist: scikit_learn
Requires-Dist: umap-learn
Requires-Dist: dill
Requires-Dist: crabnet >=2.0.5,<3.0.0
Requires-Dist: torch <2
Requires-Dist: chem_wasserstein >=1.0.8,<2.0.0
Requires-Dist: composition_based_feature_vector
Requires-Dist: matbench_genmetrics >= 0.6.1
Requires-Dist: megnet
Requires-Dist: m3gnet
Requires-Dist: gridrdf==0.3.0
Requires-Dist: matbench
Requires-Dist: pytest ; extra == "test"
Requires-Dist: ElM2D==0.4.1 ; extra == "test"
Requires-Dist: pytest-cov ; extra == "test"
Requires-Dist: pre-commit ; extra == "test"
Requires-Dist: sphinx>=4.2.0 ; extra == "test"
Requires-Dist: myst-parser==0.18.1 ; extra == "test"
Requires-Dist: nbformat >=4.2.0 ; extra == "test"
Requires-Dist: black >=22.1.0 ; extra == "test"
Requires-Dist: sphinx_rtd_theme==1.1.1 ; extra == "test"
Requires-Dist: sphinx_copybutton==0.5.1 ; extra == "test"
Requires-Dist: m3gnet ; extra == "test"
Requires-Dist: matminer<=0.7.4 ; extra == "test"
Project-URL: Source, https://github.com/sparks-baird/mat_discover
Provides-Extra: test
